ansible_lint_gitlab_ci/__init__.py
ansible_lint_gitlab_ci/main.py
ansible_lint_gitlab_ci/version.py
ansible_lint_gitlab_ci-0.1.0.dist-info/LICENSE
ansible_lint_gitlab_ci-0.1.0.dist-info/METADATA
ansible_lint_gitlab_ci-0.1.0.dist-info/WHEEL
ansible_lint_gitlab_ci-0.1.0.dist-info/entry_points.txt
ansible_lint_gitlab_ci-0.1.0.dist-info/top_level.txt
ansible_lint_gitlab_ci-0.1.0.dist-info/RECORD
