Metadata-Version: 2.1
Name: ansible-lint-gitlab-ci
Version: 0.1.0
Summary: Converts ansible-lint JSON output into GitLab friendly JUnit XML format
Home-page: https://github.com/devalphakilo/ansible-lint-gitlab-ci
Author: DevAlphaKilo
Author-email: DevAlphaKilo@gmail.com
Keywords: ansible,json,gitlab,ci/cd,xml
Classifier: Programming Language :: Python :: 3
Classifier: License :: OSI Approved :: MIT License
Classifier: Operating System :: OS Independent
Requires-Python: >=3.6
License-File: LICENSE
Requires-Dist: ansible-lint >=5.0.7
